odoo/addons/crm_partner_capital/README.rst
odoo/addons/crm_partner_capital/__init__.py
odoo/addons/crm_partner_capital/__manifest__.py
odoo/addons/crm_partner_capital/i18n/crm_partner_capital.pot
odoo/addons/crm_partner_capital/i18n/es.po
odoo/addons/crm_partner_capital/i18n/it.po
odoo/addons/crm_partner_capital/models/__init__.py
odoo/addons/crm_partner_capital/models/crm_lead.py
odoo/addons/crm_partner_capital/readme/CONTRIBUTORS.md
odoo/addons/crm_partner_capital/readme/DESCRIPTION.md
odoo/addons/crm_partner_capital/readme/USAGE.md
odoo/addons/crm_partner_capital/static/description/icon.png
odoo/addons/crm_partner_capital/static/description/index.html
odoo/addons/crm_partner_capital/tests/__init__.py
odoo/addons/crm_partner_capital/tests/test_crm_lead.py
odoo/addons/crm_partner_capital/views/crm_lead_view.xml
odoo_addon_crm_partner_capital-18.0.1.0.0.4.dist-info/METADATA
odoo_addon_crm_partner_capital-18.0.1.0.0.4.dist-info/WHEEL
odoo_addon_crm_partner_capital-18.0.1.0.0.4.dist-info/top_level.txt
odoo_addon_crm_partner_capital-18.0.1.0.0.4.dist-info/RECORD
