Metadata-Version: 2.1
Name: odoo-addon-crm_partner_capital
Version: 18.0.1.0.0.4
Requires-Python: >=3.10
Requires-Dist: odoo-addon-partner_capital==18.0.*
Requires-Dist: odoo==18.0.*
Summary: This addon extends the functionality of partner_capital
Home-page: https://github.com/OCA/crm
License: AGPL-3
Author: Binhex, Odoo Community Association (OCA)
Author-email: support@odoo-community.org
Classifier: Programming Language :: Python
Classifier: Framework :: Odoo
Classifier: Framework :: Odoo :: 18.0
Classifier: License :: OSI Approved :: GNU Affero General Public License v3
